{
  "schemaVersion": 1,
  "id": "october",
  "version": "0.0.1",
  "name": "October",
  "description": "GitHub-VMPYRC-October",
  "authors": [
    "VMPYRC"
  ],
  "contact": {
    "homepage": "https://github.com/VMPYRC/October",
    "sources": ""
  },
  "license": "All Rights Reserved",
  "icon": "assets/october/icon.png",
  "environment": "*",
  "entrypoints": {
    "main": [
      "net.mcreator.october.OctoberMod"
    ],
    "client": [
      "net.mcreator.october.ClientInit"
    ]
  },
  "depends": {
    "fabricloader": ">=0.14.21",
    "fabric": "*",
    "minecraft": "~1.20",
    "java": ">=17"
  },
  "mixins": [
    "october.mixins.json"
  ]
}